bellman/__init__.py
bellman/agents/__init__.py
bellman/agents/components.py
bellman/agents/model_based_agent.py
bellman/agents/background_planning/__init__.py
bellman/agents/background_planning/background_planning_agent.py
bellman/agents/background_planning/model_free_agent_types.py
bellman/agents/decision_time_planning/__init__.py
bellman/agents/decision_time_planning/decision_time_planning_agent.py
bellman/agents/mbpo/__init__.py
bellman/agents/mbpo/mbpo_agent.py
bellman/agents/mepo/__init__.py
bellman/agents/mepo/mepo_agent.py
bellman/agents/pets/__init__.py
bellman/agents/pets/pets_agent.py
bellman/agents/trpo/__init__.py
bellman/agents/trpo/trpo_agent.py
bellman/agents/trpo/utils.py
bellman/benchmark/__init__.py
bellman/benchmark/mepo/__init__.py
bellman/benchmark/mepo/train_eval.py
bellman/benchmark/pets/__init__.py
bellman/benchmark/pets/train_eval.py
bellman/benchmark/trpo/__init__.py
bellman/benchmark/trpo/train_eval.py
bellman/distributions/__init__.py
bellman/distributions/utils.py
bellman/drivers/__init__.py
bellman/drivers/tf_driver.py
bellman/environments/__init__.py
bellman/environments/environment_model.py
bellman/environments/initial_state_distribution_model.py
bellman/environments/mixins.py
bellman/environments/reward_model.py
bellman/environments/termination_model.py
bellman/environments/tf_wrappers.py
bellman/environments/utils.py
bellman/environments/transition_model/__init__.py
bellman/environments/transition_model/observation_transformation.py
bellman/environments/transition_model/transition_model.py
bellman/environments/transition_model/utils.py
bellman/environments/transition_model/keras_model/__init__.py
bellman/environments/transition_model/keras_model/factory_methods.py
bellman/environments/transition_model/keras_model/keras.py
bellman/environments/transition_model/keras_model/linear.py
bellman/environments/transition_model/keras_model/multilayer.py
bellman/environments/transition_model/keras_model/network.py
bellman-0.1.0.dist-info/LICENSE
bellman-0.1.0.dist-info/METADATA
bellman-0.1.0.dist-info/WHEEL
bellman-0.1.0.dist-info/top_level.txt
bellman-0.1.0.dist-info/RECORD
