Metadata-Version: 2.1
Name: bellman
Version: 0.1.0
Summary: A Toolbox for Model-Based Reinforcement Learning in TensorFlow
Home-page: https://bellman-dev
Author: The Bellman Contributors
Author-email: bellman-devs@protonmail.com
Maintainer: The Bellman Maintainers
Maintainer-email: bellman-devs@protonmail.com
License: Apache License 2.0
Project-URL: Source on GitHub, https://github.com/Bellman-devs/bellman
Project-URL: Issue tracker, https://github.com/Bellman-devs/bellman/issues
Project-URL: Documentation, https://bellman-dev/docs/latest
Keywords: machine-learning reinforcement-learning deep-learning tensorflow
Platform: UNKNOWN
Classifier: Programming Language :: Python :: 3.7
Classifier: License :: OSI Approved :: Apache Software License
Classifier: Operating System :: OS Independent
Classifier: Topic :: Scientific/Engineering :: Artificial Intelligence
Requires-Python: >=3.7,<4.0
Requires-Dist: gym (==0.17.2)
Requires-Dist: imageio-ffmpeg (==0.4.2)
Requires-Dist: imageio (==2.8.0)
Requires-Dist: matplotlib (==3.2.1)
Requires-Dist: tensorflow-probability (==0.12.1)
Requires-Dist: tensorflow (==2.4.0)
Requires-Dist: tf-agents (==0.7.1)
Provides-Extra: mujoco-py
Requires-Dist: mujoco-py (<2.1,>=2.0) ; extra == 'mujoco-py'
